boxlite/__init__.py
boxlite/boxlite.cpython-311-darwin.so
boxlite/browserbox.py
boxlite/codebox.py
boxlite/computerbox.py
boxlite/constants.py
boxlite/errors.py
boxlite/exec.py
boxlite/interactivebox.py
boxlite/runtime/boxlite-guest
boxlite/runtime/boxlite-shim
boxlite/runtime/debugfs
boxlite/runtime/libgvproxy.dylib
boxlite/runtime/libkrun.1.16.0.dylib
boxlite/runtime/libkrunfw.5.dylib
boxlite/runtime/mke2fs
boxlite/simplebox.py
boxlite/sync_api/__init__.py
boxlite/sync_api/_box.py
boxlite/sync_api/_boxlite.py
boxlite/sync_api/_codebox.py
boxlite/sync_api/_execution.py
boxlite/sync_api/_simplebox.py
boxlite/sync_api/_sync_base.py
boxlite-0.5.3.dist-info/METADATA
boxlite-0.5.3.dist-info/WHEEL
boxlite-0.5.3.dist-info/RECORD
