Metadata-Version: 2.4
Name: boxlite
Version: 0.5.3
Classifier: Development Status :: 4 - Beta
Classifier: Intended Audience :: Developers
Classifier: License :: OSI Approved :: Apache Software License
Classifier: Programming Language :: Python :: 3.10
Classifier: Programming Language :: Python :: 3.11
Classifier: Programming Language :: Python :: 3.12
Classifier: Programming Language :: Python :: 3.13
Classifier: Programming Language :: Rust
Classifier: Operating System :: MacOS
Classifier: Operating System :: POSIX :: Linux
Classifier: Topic :: Scientific/Engineering :: Artificial Intelligence
Classifier: Topic :: Security
Classifier: Topic :: System :: Emulators
Requires-Dist: pytest>=7.0 ; extra == 'dev'
Requires-Dist: pytest-asyncio>=0.21 ; extra == 'dev'
Requires-Dist: greenlet>=3.0.0 ; extra == 'sync'
Provides-Extra: dev
Provides-Extra: sync
Summary: Python bindings for Boxlite runtime
Keywords: sandbox,virtual machine,vm,ai agents,code execution,isolation,container,security,kvm,hypervisor
Author: Dorian Zheng
License-Expression: Apache-2.0
Requires-Python: >=3.10
Project-URL: Documentation, https://github.com/boxlite-ai/boxlite/tree/main/docs
Project-URL: Homepage, https://github.com/boxlite-ai/boxlite
Project-URL: Issues, https://github.com/boxlite-ai/boxlite/issues
Project-URL: Repository, https://github.com/boxlite-ai/boxlite
